MANIFEST.in
README.txt
requirements.txt
setup.py
config/config-template.json
config/logging.conf
rax_autoscaler.egg-info/PKG-INFO
rax_autoscaler.egg-info/SOURCES.txt
rax_autoscaler.egg-info/dependency_links.txt
rax_autoscaler.egg-info/entry_points.txt
rax_autoscaler.egg-info/requires.txt
rax_autoscaler.egg-info/top_level.txt
raxas/__init__.py
raxas/auth.py
raxas/autoscale.py
raxas/autoscale_config.py
raxas/colouredconsolehandler.py
raxas/common.py
raxas/enums.py
raxas/monitoring.py
raxas/scaling_group.py
raxas/version.py
raxas/core_plugins/__init__.py
raxas/core_plugins/base.py
raxas/core_plugins/newrelic.py
raxas/core_plugins/raxclb.py
raxas/core_plugins/raxmon.py
raxas/core_plugins/raxmon_autoscale.py
tests/__init__.py
tests/base_test.py
tests/test_auth.py
tests/test_common.py
tests/test_monitoring.py
tests/test_newrelic.py
tests/test_raxauto.py
tests/test_raxclb.py
tests/test_scaling_group.py