Metadata-Version: 1.1
Name: rax-autoscaler
Version: 0.4.0
Summary: Rackspace Auto Scale made easy
Home-page: https://github.com/boxidau/rax-autoscaler
Author: Simone Soldateschi
Author-email: simone.soldateschi@rackspace.co.uk
License: Apache License, Version 2.0
Keywords: rax rackspace autoscale scaling devops cloud openstack
Platform: any
Classifier: Development Status :: 4 - Beta
Classifier: License :: OSI Approved :: Apache Software License
Classifier: Programming Language :: Python :: 2
Classifier: Environment :: Console
Classifier: Intended Audience :: Information Technology
Classifier: Natural Language :: English
Provides: raxas.ext
